d3plus/__init__.py
d3plus/d3plus.py
d3plus/examples.py
d3plus/data/__init__.py
d3plus/utils/__init__.py
d3plus-0.1.0.dist-info/LICENSE
d3plus-0.1.0.dist-info/METADATA
d3plus-0.1.0.dist-info/WHEEL
d3plus-0.1.0.dist-info/top_level.txt
d3plus-0.1.0.dist-info/RECORD
