Metadata-Version: 2.1
Name: d3plus
Version: 0.1.0
Summary: Python package d3plus
Home-page: https://github.com/erdogant/d3plus
Download-URL: https://github.com/erdogant/d3plus/archive/0.1.0.tar.gz
Author: Erdogan Taskesen
Author-email: erdogant@gmail.com
Classifier: Programming Language :: Python :: 3
Classifier: License :: OSI Approved :: MIT License
Classifier: Operating System :: OS Independent
Requires-Python: >=3
License-File: LICENSE
Requires-Dist: matplotlib
Requires-Dist: numpy
Requires-Dist: pandas
Requires-Dist: tqdm
Requires-Dist: requests
Requires-Dist: datazets
